Workbook

Sheet Dataset
A1: Customer_ID | B1: Customer_Name | C1: Region | D1: Product_Category | E1: Sales | F1: Quantity | G1: Discount | H1: Order_Date | I1: Profit | J1: Adjusted Profit (Scenario) | K1: Month | L1: Month Key | M1: Timestamp NOW() | N1: Sales Rank
A2: CUST019 | B2: James Davis | C2: West | D2: Books | E2: 1036.09 | F2: 4 | G2: 0.2 | H2: 45392 | I2: 331.55 | J2: =I2+E2*(G2-'What-If Analysis'!$B$4) -> 435.159 | K2: =MONTH(H2) -> 4 | L2: =TEXT(H2,"yyyy-mm") -> 2024-04 | M2: =NOW() -> 46324.535 | N2: =_xlfn.RANK.EQ(E2,$E$2:$E$201,0) -> 80
A3: CUST012 | B3: Robert Anderson | C3: West | D3: Clothing | E3: 1101.28 | F3: 3 | G3: 0.2 | H3: 45393 | I3: 440.51 | J3: =I3+E3*(G3-'What-If Analysis'!$B$4) -> 550.638 | K3: =MONTH(H3) -> 4 | L3: =TEXT(H3,"yyyy-mm") -> 2024-04 | M3: =NOW() -> 46324.535 | N3: =_xlfn.RANK.EQ(E3,$E$2:$E$201,0) -> 66
A4: CUST017 | B4: James Taylor | C4: East | D4: Books | E4: 713.34 | F4: 17 | G4: 0 | H4: 45396 | I4: 285.34 | J4: =I4+E4*(G4-'What-If Analysis'!$B$4) -> 214.006 | K4: =MONTH(H4) -> 4 | L4: =TEXT(H4,"yyyy-mm") -> 2024-04 | M4: =NOW() -> 46324.535 | N4: =_xlfn.RANK.EQ(E4,$E$2:$E$201,0) -> 162
A5: CUST005 | B5: Robert Anderson | C5: South | D5: Electronics | E5: 760.93 | F5: 4 | G5: 0.15 | H5: 45396 | I5: 161.7 | J5: =I5+E5*(G5-'What-If Analysis'!$B$4) -> 199.7465 | K5: =MONTH(H5) -> 4 | L5: =TEXT(H5,"yyyy-mm") -> 2024-04 | M5: =NOW() -> 46324.535 | N5: =_xlfn.RANK.EQ(E5,$E$2:$E$201,0) -> 151
A6: CUST030 | B6: James Wilson | C6: North | D6: Books | E6: 847 | F6: 12 | G6: 0.2 | H6: 45397 | I6: 271.04 | J6: =I6+E6*(G6-'What-If Analysis'!$B$4) -> 355.74 | K6: =MONTH(H6) -> 4 | L6: =TEXT(H6,"yyyy-mm") -> 2024-04 | M6: =NOW() -> 46324.535 | N6: =_xlfn.RANK.EQ(E6,$E$2:$E$201,0) -> 131
A7: CUST007 | B7: Michael Anderson | C7: North | D7: Furniture | E7: 965.64 | F7: 8 | G7: 0.1 | H7: 45398 | I7: 304.18 | J7: =I7+E7*(G7-'What-If Analysis'!$B$4) -> 304.18 | K7: =MONTH(H7) -> 4 | L7: =TEXT(H7,"yyyy-mm") -> 2024-04 | M7: =NOW() -> 46324.535 | N7: =_xlfn.RANK.EQ(E7,$E$2:$E$201,0) -> 104
A8: CUST001 | B8: Linda Wilson | C8: West | D8: Electronics | E8: 1317.53 | F8: 12 | G8: 0.05 | H8: 45398 | I8: 312.91 | J8: =I8+E8*(G8-'What-If Analysis'!$B$4) -> 247.0335 | K8: =MONTH(H8) -> 4 | L8: =TEXT(H8,"yyyy-mm") -> 2024-04 | M8: =NOW() -> 46324.535 | N8: =_xlfn.RANK.EQ(E8,$E$2:$E$201,0) -> 26
A9: CUST026 | B9: Mary Davis | C9: East | D9: Furniture | E9: 1074.47 | F9: 6 | G9: 0.2 | H9: 45401 | I9: 300.85 | J9: =I9+E9*(G9-'What-If Analysis'!$B$4) -> 408.297 | K9: =MONTH(H9) -> 4 | L9: =TEXT(H9,"yyyy-mm") -> 2024-04 | M9: =NOW() -> 46324.535 | N9: =_xlfn.RANK.EQ(E9,$E$2:$E$201,0) -> 75
A10: CUST009 | B10: Linda Jackson | C10: Central | D10: Books | E10: 501.54 | F10: 11 | G10: 0.05 | H10: 45401 | I10: 190.59 | J10: =I10+E10*(G10-'What-If Analysis'!$B$4) -> 165.513 | K10: =MONTH(H10) -> 4 | L10: =TEXT(H10,"yyyy-mm") -> 2024-04 | M10: =NOW() -> 46324.535 | N10: =_xlfn.RANK.EQ(E10,$E$2:$E$201,0) -> 189
A11: CUST010 | B11: David Thomas | C11: Central | D11: Clothing | E11: 737.31 | F11: 2 | G11: 0.05 | H11: 45401 | I11: 350.22 | J11: =I11+E11*(G11-'What-If Analysis'!$B$4) -> 313.3545 | K11: =MONTH(H11) -> 4 | L11: =TEXT(H11,"yyyy-mm") -> 2024-04 | M11: =NOW() -> 46324.535 | N11: =_xlfn.RANK.EQ(E11,$E$2:$E$201,0) -> 158
A12: CUST014 | B12: Emma Davis | C12: West | D12: Office Supplies | E12: 1572.82 | F12: 6 | G12: 0.05 | H12: 45402 | I12: 672.38 | J12: =I12+E12*(G12-'What-If Analysis'!$B$4) -> 593.739 | K12: =MONTH(H12) -> 4 | L12: =TEXT(H12,"yyyy-mm") -> 2024-04 | M12: =NOW() -> 46324.535 | N12: =_xlfn.RANK.EQ(E12,$E$2:$E$201,0) -> 6
A13: CUST014 | B13: David Thomas | C13: Central | D13: Books | E13: 1343.13 | F13: 14 | G13: 0.15 | H13: 45404 | I13: 456.66 | J13: =I13+E13*(G13-'What-If Analysis'!$B$4) -> 523.8165 | K13: =MONTH(H13) -> 4 | L13: =TEXT(H13,"yyyy-mm") -> 2024-04 | M13: =NOW() -> 46324.535 | N13: =_xlfn.RANK.EQ(E13,$E$2:$E$201,0) -> 24
... A201: CUST016 | B201: David Thomas | C201: South | D201: Clothing | E201: 928.32 | F201: 2 | G201: 0.05 | H201: 45754 | I201: 440.95 | J201: =I201+E201*(G201-'What-If Analysis'!$B$4) -> 394.534 | K201: =MONTH(H201) -> 4 | L201: =TEXT(H201,"yyyy-mm") -> 2025-04 | M201: =NOW() -> 46324.535 | N201: =_xlfn.RANK.EQ(E201,$E$2:$E$201,0) -> 112

Sheet Customer Ranking
A1: Customer ID | B1: Total Sales | C1: Total Profit | D1: Orders | E1: Rank | F1: Segment | G1: Lookup ID | H1: INDEX MATCH Sales
A2: CUST015 | B2: =SUMIF(Dataset!$A$2:$A$201,A2,Dataset!$E$2:$E$201) -> 11611.06 | C2: =SUMIF(Dataset!$A$2:$A$201,A2,Dataset!$I$2:$I$201) -> 4201.59 | D2: =COUNTIF(Dataset!$A$2:$A$201,A2) -> 11 | E2: =_xlfn.RANK.EQ(B2,$B$2:$B$31,0) -> 1 | F2: =IF(E2<=10,"TOP 10","STANDARD") -> TOP 10 | G2: =A2 -> CUST015 | H2: =INDEX($B$2:$B$31,MATCH(G2,$A$2:$A$31,0)) -> 11611.06
A3: CUST028 | B3: =SUMIF(Dataset!$A$2:$A$201,A3,Dataset!$E$2:$E$201) -> 10293.87 | C3: =SUMIF(Dataset!$A$2:$A$201,A3,Dataset!$I$2:$I$201) -> 3541.02 | D3: =COUNTIF(Dataset!$A$2:$A$201,A3) -> 12 | E3: =_xlfn.RANK.EQ(B3,$B$2:$B$31,0) -> 2 | F3: =IF(E3<=10,"TOP 10","STANDARD") -> TOP 10 | G3: =A3 -> CUST028 | H3: =INDEX($B$2:$B$31,MATCH(G3,$A$2:$A$31,0)) -> 10293.87
A4: CUST007 | B4: =SUMIF(Dataset!$A$2:$A$201,A4,Dataset!$E$2:$E$201) -> 9941.88 | C4: =SUMIF(Dataset!$A$2:$A$201,A4,Dataset!$I$2:$I$201) -> 3936.26 | D4: =COUNTIF(Dataset!$A$2:$A$201,A4) -> 10 | E4: =_xlfn.RANK.EQ(B4,$B$2:$B$31,0) -> 3 | F4: =IF(E4<=10,"TOP 10","STANDARD") -> TOP 10 | G4: =A4 -> CUST007 | H4: =INDEX($B$2:$B$31,MATCH(G4,$A$2:$A$31,0)) -> 9941.88
A5: CUST008 | B5: =SUMIF(Dataset!$A$2:$A$201,A5,Dataset!$E$2:$E$201) -> 9760.8 | C5: =SUMIF(Dataset!$A$2:$A$201,A5,Dataset!$I$2:$I$201) -> 3442.48 | D5: =COUNTIF(Dataset!$A$2:$A$201,A5) -> 10 | E5: =_xlfn.RANK.EQ(B5,$B$2:$B$31,0) -> 4 | F5: =IF(E5<=10,"TOP 10","STANDARD") -> TOP 10 | G5: =A5 -> CUST008 | H5: =INDEX($B$2:$B$31,MATCH(G5,$A$2:$A$31,0)) -> 9760.8
A6: CUST026 | B6: =SUMIF(Dataset!$A$2:$A$201,A6,Dataset!$E$2:$E$201) -> 9371.81 | C6: =SUMIF(Dataset!$A$2:$A$201,A6,Dataset!$I$2:$I$201) -> 2922.02 | D6: =COUNTIF(Dataset!$A$2:$A$201,A6) -> 9 | E6: =_xlfn.RANK.EQ(B6,$B$2:$B$31,0) -> 5 | F6: =IF(E6<=10,"TOP 10","STANDARD") -> TOP 10 | G6: =A6 -> CUST026 | H6: =INDEX($B$2:$B$31,MATCH(G6,$A$2:$A$31,0)) -> 9371.81
A7: CUST021 | B7: =SUMIF(Dataset!$A$2:$A$201,A7,Dataset!$E$2:$E$201) -> 8740.18 | C7: =SUMIF(Dataset!$A$2:$A$201,A7,Dataset!$I$2:$I$201) -> 2848.62 | D7: =COUNTIF(Dataset!$A$2:$A$201,A7) -> 8 | E7: =_xlfn.RANK.EQ(B7,$B$2:$B$31,0) -> 6 | F7: =IF(E7<=10,"TOP 10","STANDARD") -> TOP 10 | G7: =A7 -> CUST021 | H7: =INDEX($B$2:$B$31,MATCH(G7,$A$2:$A$31,0)) -> 8740.18
A8: CUST003 | B8: =SUMIF(Dataset!$A$2:$A$201,A8,Dataset!$E$2:$E$201) -> 8490.18 | C8: =SUMIF(Dataset!$A$2:$A$201,A8,Dataset!$I$2:$I$201) -> 2652.75 | D8: =COUNTIF(Dataset!$A$2:$A$201,A8) -> 9 | E8: =_xlfn.RANK.EQ(B8,$B$2:$B$31,0) -> 7 | F8: =IF(E8<=10,"TOP 10","STANDARD") -> TOP 10 | G8: =A8 -> CUST003 | H8: =INDEX($B$2:$B$31,MATCH(G8,$A$2:$A$31,0)) -> 8490.18
A9: CUST012 | B9: =SUMIF(Dataset!$A$2:$A$201,A9,Dataset!$E$2:$E$201) -> 8339 | C9: =SUMIF(Dataset!$A$2:$A$201,A9,Dataset!$I$2:$I$201) -> 2988.71 | D9: =COUNTIF(Dataset!$A$2:$A$201,A9) -> 9 | E9: =_xlfn.RANK.EQ(B9,$B$2:$B$31,0) -> 8 | F9: =IF(E9<=10,"TOP 10","STANDARD") -> TOP 10 | G9: =A9 -> CUST012 | H9: =INDEX($B$2:$B$31,MATCH(G9,$A$2:$A$31,0)) -> 8339
A10: CUST030 | B10: =SUMIF(Dataset!$A$2:$A$201,A10,Dataset!$E$2:$E$201) -> 7928.71 | C10: =SUMIF(Dataset!$A$2:$A$201,A10,Dataset!$I$2:$I$201) -> 2965.48 | D10: =COUNTIF(Dataset!$A$2:$A$201,A10) -> 9 | E10: =_xlfn.RANK.EQ(B10,$B$2:$B$31,0) -> 9 | F10: =IF(E10<=10,"TOP 10","STANDARD") -> TOP 10 | G10: =A10 -> CUST030 | H10: =INDEX($B$2:$B$31,MATCH(G10,$A$2:$A$31,0)) -> 7928.71
A11: CUST004 | B11: =SUMIF(Dataset!$A$2:$A$201,A11,Dataset!$E$2:$E$201) -> 7813.59 | C11: =SUMIF(Dataset!$A$2:$A$201,A11,Dataset!$I$2:$I$201) -> 3211.82 | D11: =COUNTIF(Dataset!$A$2:$A$201,A11) -> 7 | E11: =_xlfn.RANK.EQ(B11,$B$2:$B$31,0) -> 10 | F11: =IF(E11<=10,"TOP 10","STANDARD") -> TOP 10 | G11: =A11 -> CUST004 | H11: =INDEX($B$2:$B$31,MATCH(G11,$A$2:$A$31,0)) -> 7813.59
A12: CUST024 | B12: =SUMIF(Dataset!$A$2:$A$201,A12,Dataset!$E$2:$E$201) -> 7583.13 | C12: =SUMIF(Dataset!$A$2:$A$201,A12,Dataset!$I$2:$I$201) -> 2492.1 | D12: =COUNTIF(Dataset!$A$2:$A$201,A12) -> 7 | E12: =_xlfn.RANK.EQ(B12,$B$2:$B$31,0) -> 11 | F12: =IF(E12<=10,"TOP 10","STANDARD") -> STANDARD | G12: =A12 -> CUST024 | H12: =INDEX($B$2:$B$31,MATCH(G12,$A$2:$A$31,0)) -> 7583.13
A13: CUST014 | B13: =SUMIF(Dataset!$A$2:$A$201,A13,Dataset!$E$2:$E$201) -> 6729.89 | C13: =SUMIF(Dataset!$A$2:$A$201,A13,Dataset!$I$2:$I$201) -> 2507.18 | D13: =COUNTIF(Dataset!$A$2:$A$201,A13) -> 6 | E13: =_xlfn.RANK.EQ(B13,$B$2:$B$31,0) -> 12 | F13: =IF(E13<=10,"TOP 10","STANDARD") -> STANDARD | G13: =A13 -> CUST014 | H13: =INDEX($B$2:$B$31,MATCH(G13,$A$2:$A$31,0)) -> 6729.89
... A31: CUST006 | B31: =SUMIF(Dataset!$A$2:$A$201,A31,Dataset!$E$2:$E$201) -> 2699.75 | C31: =SUMIF(Dataset!$A$2:$A$201,A31,Dataset!$I$2:$I$201) -> 837.06 | D31: =COUNTIF(Dataset!$A$2:$A$201,A31) -> 2 | E31: =_xlfn.RANK.EQ(B31,$B$2:$B$31,0) -> 30 | F31: =IF(E31<=10,"TOP 10","STANDARD") -> STANDARD | G31: =A31 -> CUST006 | H31: =INDEX($B$2:$B$31,MATCH(G31,$A$2:$A$31,0)) -> 2699.75

Sheet What-If Analysis
A1: DISCOUNT SCENARIO | B1: VALUE | C1: DESCRIPTION
A2: Current total sales | B2: =SUM(Dataset!E2:E201) -> 195217.76 | C2: Original sales (before scenario adjustment)
A3: Current total profit | B3: =SUM(Dataset!I2:I201) -> 68287.01 | C3: Original profit
A4: Scenario discount | B4: 0.1 | C4: Editable: change to 0%, 5%, 10%, 15%, 20%
A5: Adjusted total profit | B5: =SUM(Dataset!J2:J201) -> 68037.992 | C5: Assumes each sale profit changes by Sales × (original discount − scenario discount)
A6: Profit change | B6: =B5-B3 -> -249.0185 | C6: Adjusted minus current
A7: Profit change % | B7: =IFERROR(B6/B3,0) -> -0.0036466452 | C7: Relative to original total profit
A10: Scenario Discount | B10: Estimated Total Profit | C10: Change vs Actual
A11: 0 | B11: =$B$3+SUMPRODUCT(Dataset!$E$2:$E$201,Dataset!$G$2:$G$201-A11) -> 87559.768 | C11: =B11-$B$3 -> 19272.758
A12: 0.05 | B12: =$B$3+SUMPRODUCT(Dataset!$E$2:$E$201,Dataset!$G$2:$G$201-A12) -> 77798.88 | C12: =B12-$B$3 -> 9511.8695
A13: 0.1 | B13: =$B$3+SUMPRODUCT(Dataset!$E$2:$E$201,Dataset!$G$2:$G$201-A13) -> 68037.992 | C13: =B13-$B$3 -> -249.0185
A14: 0.15 | B14: =$B$3+SUMPRODUCT(Dataset!$E$2:$E$201,Dataset!$G$2:$G$201-A14) -> 58277.104 | C14: =B14-$B$3 -> -10009.906
A15: 0.2 | B15: =$B$3+SUMPRODUCT(Dataset!$E$2:$E$201,Dataset!$G$2:$G$201-A15) -> 48516.216 | C15: =B15-$B$3 -> -19770.795
A16: 0.25 | B16: =$B$3+SUMPRODUCT(Dataset!$E$2:$E$201,Dataset!$G$2:$G$201-A16) -> 38755.327 | C16: =B16-$B$3 -> -29531.683

Sheet Descriptive Statistics
A1: METRIC | B1: SALES | C1: PROFIT | D1: DISCOUNT | E1: QUANTITY
A2: Count | B2: =COUNT(Dataset!E2:E201) -> 200 | C2: =COUNT(Dataset!I2:I201) -> 200 | D2: =COUNT(Dataset!G2:G201) -> 200 | E2: =COUNT(Dataset!F2:F201) -> 200
A3: Sum | B3: =SUM(Dataset!E2:E201) -> 195217.76 | C3: =SUM(Dataset!I2:I201) -> 68287.01 | D3: =SUM(Dataset!G2:G201) -> 19.45 | E3: =SUM(Dataset!F2:F201) -> 1999
A4: Mean | B4: =AVERAGE(Dataset!E2:E201) -> 976.0888 | C4: =AVERAGE(Dataset!I2:I201) -> 341.43505 | D4: =AVERAGE(Dataset!G2:G201) -> 0.09725 | E4: =AVERAGE(Dataset!F2:F201) -> 9.995
A5: Median | B5: =MEDIAN(Dataset!E2:E201) -> 976.72 | C5: =MEDIAN(Dataset!I2:I201) -> 332.255 | D5: =MEDIAN(Dataset!G2:G201) -> 0.1 | E5: =MEDIAN(Dataset!F2:F201) -> 10
A6: Minimum | B6: =MIN(Dataset!E2:E201) -> 258.51 | C6: =MIN(Dataset!I2:I201) -> 64.63 | D6: =MIN(Dataset!G2:G201) -> 0 | E6: =MIN(Dataset!F2:F201) -> 1
A7: Maximum | B7: =MAX(Dataset!E2:E201) -> 1923.66 | C7: =MAX(Dataset!I2:I201) -> 769.46 | D7: =MAX(Dataset!G2:G201) -> 0.2 | E7: =MAX(Dataset!F2:F201) -> 19
A8: Std Deviation | B8: =_xlfn.STDEV.S(Dataset!E2:E201) -> 299.27376 | C8: =_xlfn.STDEV.S(Dataset!I2:I201) -> 135.76619 | D8: =_xlfn.STDEV.S(Dataset!G2:G201) -> 0.072326295 | E8: =_xlfn.STDEV.S(Dataset!F2:F201) -> 5.646627
A9: Variance | B9: =_xlfn.VAR.S(Dataset!E2:E201) -> 89564.783 | C9: =_xlfn.VAR.S(Dataset!I2:I201) -> 18432.459 | D9: =_xlfn.VAR.S(Dataset!G2:G201) -> 0.005231093 | E9: =_xlfn.VAR.S(Dataset!F2:F201) -> 31.884397
A10: 25th Percentile | B10: =_xlfn.PERCENTILE.INC(Dataset!E2:E201,0.25) -> 761.8375 | C10: =_xlfn.PERCENTILE.INC(Dataset!I2:I201,0.25) -> 240.8425 | D10: =_xlfn.PERCENTILE.INC(Dataset!G2:G201,0.25) -> 0.05 | E10: =_xlfn.PERCENTILE.INC(Dataset!F2:F201,0.25) -> 5
A11: 75th Percentile | B11: =_xlfn.PERCENTILE.INC(Dataset!E2:E201,0.75) -> 1173.0075 | C11: =_xlfn.PERCENTILE.INC(Dataset!I2:I201,0.75) -> 440.0375 | D11: =_xlfn.PERCENTILE.INC(Dataset!G2:G201,0.75) -> 0.15 | E11: =_xlfn.PERCENTILE.INC(Dataset!F2:F201,0.75) -> 15

Sheet Regression
A1: PROFIT VS SALES REGRESSION | B1: VALUE | C1: INTERPRETATION
A2: Observations | B2: 200 | C2: Transaction count
A3: Slope | B3: 0.35085599 | C3: Estimated change in profit per unit of sales
A4: Intercept | B4: -1.0315505 | C4: Predicted profit when sales are zero
A5: R-squared | B5: 0.5981523 | C5: Share of variation in profit explained by sales
A6: Correlation | B6: 0.77340306 | C6: Pearson correlation
A7: Residual standard error | B7: 86.281231 | C7: Standard error of prediction
A8: Slope t-statistic | B8: 17.167527 | C8: Slope divided by its standard error
A9: Model | B9: Profit = Intercept + Slope × Sales | C9: Ordinary least squares; based on all 200 original transactions

Sheet Monthly Trends
A1: Month | B1: Total Sales | C1: Total Profit | D1: Orders | E1: Sales Growth | F1: Trend | G1: Timestamp
A2: 2024-04 | B2: =SUMIF(Dataset!$L$2:$L$201,A2,Dataset!$E$2:$E$201) -> 19029.96 | C2: =SUMIF(Dataset!$L$2:$L$201,A2,Dataset!$I$2:$I$201) -> 6244.01 | D2: =COUNTIF(Dataset!$L$2:$L$201,A2) -> 19 | E2: =0 -> 0 | F2: =IF(E2>0,"▲ UP",IF(E2<0,"▼ DOWN","— FLAT")) -> — FLAT | G2: =NOW() -> 46324.535
A3: 2024-05 | B3: =SUMIF(Dataset!$L$2:$L$201,A3,Dataset!$E$2:$E$201) -> 18507.34 | C3: =SUMIF(Dataset!$L$2:$L$201,A3,Dataset!$I$2:$I$201) -> 6121.35 | D3: =COUNTIF(Dataset!$L$2:$L$201,A3) -> 21 | E3: =IFERROR(B3/B2-1,0) -> -0.027463011 | F3: =IF(E3>0,"▲ UP",IF(E3<0,"▼ DOWN","— FLAT")) -> ▼ DOWN | G3: =NOW() -> 46324.535
A4: 2024-06 | B4: =SUMIF(Dataset!$L$2:$L$201,A4,Dataset!$E$2:$E$201) -> 20187.51 | C4: =SUMIF(Dataset!$L$2:$L$201,A4,Dataset!$I$2:$I$201) -> 6918 | D4: =COUNTIF(Dataset!$L$2:$L$201,A4) -> 20 | E4: =IFERROR(B4/B3-1,0) -> 0.090783981 | F4: =IF(E4>0,"▲ UP",IF(E4<0,"▼ DOWN","— FLAT")) -> ▲ UP | G4: =NOW() -> 46324.535
A5: 2024-07 | B5: =SUMIF(Dataset!$L$2:$L$201,A5,Dataset!$E$2:$E$201) -> 11609.04 | C5: =SUMIF(Dataset!$L$2:$L$201,A5,Dataset!$I$2:$I$201) -> 3743.85 | D5: =COUNTIF(Dataset!$L$2:$L$201,A5) -> 12 | E5: =IFERROR(B5/B4-1,0) -> -0.42493948 | F5: =IF(E5>0,"▲ UP",IF(E5<0,"▼ DOWN","— FLAT")) -> ▼ DOWN | G5: =NOW() -> 46324.535
A6: 2024-08 | B6: =SUMIF(Dataset!$L$2:$L$201,A6,Dataset!$E$2:$E$201) -> 10091.7 | C6: =SUMIF(Dataset!$L$2:$L$201,A6,Dataset!$I$2:$I$201) -> 3302.84 | D6: =COUNTIF(Dataset!$L$2:$L$201,A6) -> 10 | E6: =IFERROR(B6/B5-1,0) -> -0.13070331 | F6: =IF(E6>0,"▲ UP",IF(E6<0,"▼ DOWN","— FLAT")) -> ▼ DOWN | G6: =NOW() -> 46324.535
A7: 2024-09 | B7: =SUMIF(Dataset!$L$2:$L$201,A7,Dataset!$E$2:$E$201) -> 20533.5 | C7: =SUMIF(Dataset!$L$2:$L$201,A7,Dataset!$I$2:$I$201) -> 7457.52 | D7: =COUNTIF(Dataset!$L$2:$L$201,A7) -> 20 | E7: =IFERROR(B7/B6-1,0) -> 1.0346919 | F7: =IF(E7>0,"▲ UP",IF(E7<0,"▼ DOWN","— FLAT")) -> ▲ UP | G7: =NOW() -> 46324.535
A8: 2024-10 | B8: =SUMIF(Dataset!$L$2:$L$201,A8,Dataset!$E$2:$E$201) -> 14215.24 | C8: =SUMIF(Dataset!$L$2:$L$201,A8,Dataset!$I$2:$I$201) -> 4861.7 | D8: =COUNTIF(Dataset!$L$2:$L$201,A8) -> 14 | E8: =IFERROR(B8/B7-1,0) -> -0.30770497 | F8: =IF(E8>0,"▲ UP",IF(E8<0,"▼ DOWN","— FLAT")) -> ▼ DOWN | G8: =NOW() -> 46324.535
A9: 2024-11 | B9: =SUMIF(Dataset!$L$2:$L$201,A9,Dataset!$E$2:$E$201) -> 20135.03 | C9: =SUMIF(Dataset!$L$2:$L$201,A9,Dataset!$I$2:$I$201) -> 6814.88 | D9: =COUNTIF(Dataset!$L$2:$L$201,A9) -> 20 | E9: =IFERROR(B9/B8-1,0) -> 0.41643968 | F9: =IF(E9>0,"▲ UP",IF(E9<0,"▼ DOWN","— FLAT")) -> ▲ UP | G9: =NOW() -> 46324.535
A10: 2024-12 | B10: =SUMIF(Dataset!$L$2:$L$201,A10,Dataset!$E$2:$E$201) -> 11120.04 | C10: =SUMIF(Dataset!$L$2:$L$201,A10,Dataset!$I$2:$I$201) -> 3549.99 | D10: =COUNTIF(Dataset!$L$2:$L$201,A10) -> 11 | E10: =IFERROR(B10/B9-1,0) -> -0.44772667 | F10: =IF(E10>0,"▲ UP",IF(E10<0,"▼ DOWN","— FLAT")) -> ▼ DOWN | G10: =NOW() -> 46324.535
A11: 2025-01 | B11: =SUMIF(Dataset!$L$2:$L$201,A11,Dataset!$E$2:$E$201) -> 14914.65 | C11: =SUMIF(Dataset!$L$2:$L$201,A11,Dataset!$I$2:$I$201) -> 5763.4 | D11: =COUNTIF(Dataset!$L$2:$L$201,A11) -> 16 | E11: =IFERROR(B11/B10-1,0) -> 0.34124068 | F11: =IF(E11>0,"▲ UP",IF(E11<0,"▼ DOWN","— FLAT")) -> ▲ UP | G11: =NOW() -> 46324.535
A12: 2025-02 | B12: =SUMIF(Dataset!$L$2:$L$201,A12,Dataset!$E$2:$E$201) -> 14006.36 | C12: =SUMIF(Dataset!$L$2:$L$201,A12,Dataset!$I$2:$I$201) -> 5039.23 | D12: =COUNTIF(Dataset!$L$2:$L$201,A12) -> 14 | E12: =IFERROR(B12/B11-1,0) -> -0.060899183 | F12: =IF(E12>0,"▲ UP",IF(E12<0,"▼ DOWN","— FLAT")) -> ▼ DOWN | G12: =NOW() -> 46324.535
A13: 2025-03 | B13: =SUMIF(Dataset!$L$2:$L$201,A13,Dataset!$E$2:$E$201) -> 17655.22 | C13: =SUMIF(Dataset!$L$2:$L$201,A13,Dataset!$I$2:$I$201) -> 7071.39 | D13: =COUNTIF(Dataset!$L$2:$L$201,A13) -> 19 | E13: =IFERROR(B13/B12-1,0) -> 0.26051451 | F13: =IF(E13>0,"▲ UP",IF(E13<0,"▼ DOWN","— FLAT")) -> ▲ UP | G13: =NOW() -> 46324.535
A14: 2025-04 | B14: =SUMIF(Dataset!$L$2:$L$201,A14,Dataset!$E$2:$E$201) -> 3212.17 | C14: =SUMIF(Dataset!$L$2:$L$201,A14,Dataset!$I$2:$I$201) -> 1398.85 | D14: =COUNTIF(Dataset!$L$2:$L$201,A14) -> 4 | E14: =IFERROR(B14/B13-1,0) -> -0.81806117 | F14: =IF(E14>0,"▲ UP",IF(E14<0,"▼ DOWN","— FLAT")) -> ▼ DOWN | G14: =NOW() -> 46324.535

Sheet Region Product Analysis
A1: REGION / CATEGORY | B1: Books | C1: Clothing | D1: Electronics | E1: Furniture | F1: Office Supplies | G1: TOTAL SALES | H1: TOTAL PROFIT | I1: ORDERS
A2: Central | B2: =SUMIFS(Dataset!$E$2:$E$201,Dataset!$C$2:$C$201,$A2,Dataset!$D$2:$D$201,B$1) -> 11297.15 | C2: =SUMIFS(Dataset!$E$2:$E$201,Dataset!$C$2:$C$201,$A2,Dataset!$D$2:$D$201,C$1) -> 12200.26 | D2: =SUMIFS(Dataset!$E$2:$E$201,Dataset!$C$2:$C$201,$A2,Dataset!$D$2:$D$201,D$1) -> 6621.24 | E2: =SUMIFS(Dataset!$E$2:$E$201,Dataset!$C$2:$C$201,$A2,Dataset!$D$2:$D$201,E$1) -> 4876.96 | F2: =SUMIFS(Dataset!$E$2:$E$201,Dataset!$C$2:$C$201,$A2,Dataset!$D$2:$D$201,F$1) -> 8472.72 | G2: =SUM(B2:F2) -> 43468.33 | H2: =SUMIF(Dataset!$C$2:$C$201,A2,Dataset!$I$2:$I$201) -> 16068.4 | I2: =COUNTIF(Dataset!$C$2:$C$201,A2) -> 44
A3: East | B3: =SUMIFS(Dataset!$E$2:$E$201,Dataset!$C$2:$C$201,$A3,Dataset!$D$2:$D$201,B$1) -> 11389.09 | C3: =SUMIFS(Dataset!$E$2:$E$201,Dataset!$C$2:$C$201,$A3,Dataset!$D$2:$D$201,C$1) -> 2401.45 | D3: =SUMIFS(Dataset!$E$2:$E$201,Dataset!$C$2:$C$201,$A3,Dataset!$D$2:$D$201,D$1) -> 2869.54 | E3: =SUMIFS(Dataset!$E$2:$E$201,Dataset!$C$2:$C$201,$A3,Dataset!$D$2:$D$201,E$1) -> 7592.34 | F3: =SUMIFS(Dataset!$E$2:$E$201,Dataset!$C$2:$C$201,$A3,Dataset!$D$2:$D$201,F$1) -> 8189.22 | G3: =SUM(B3:F3) -> 32441.64 | H3: =SUMIF(Dataset!$C$2:$C$201,A3,Dataset!$I$2:$I$201) -> 11638.59 | I3: =COUNTIF(Dataset!$C$2:$C$201,A3) -> 32
A4: North | B4: =SUMIFS(Dataset!$E$2:$E$201,Dataset!$C$2:$C$201,$A4,Dataset!$D$2:$D$201,B$1) -> 8037.01 | C4: =SUMIFS(Dataset!$E$2:$E$201,Dataset!$C$2:$C$201,$A4,Dataset!$D$2:$D$201,C$1) -> 8422.82 | D4: =SUMIFS(Dataset!$E$2:$E$201,Dataset!$C$2:$C$201,$A4,Dataset!$D$2:$D$201,D$1) -> 8191.71 | E4: =SUMIFS(Dataset!$E$2:$E$201,Dataset!$C$2:$C$201,$A4,Dataset!$D$2:$D$201,E$1) -> 6978.08 | F4: =SUMIFS(Dataset!$E$2:$E$201,Dataset!$C$2:$C$201,$A4,Dataset!$D$2:$D$201,F$1) -> 3345.8 | G4: =SUM(B4:F4) -> 34975.42 | H4: =SUMIF(Dataset!$C$2:$C$201,A4,Dataset!$I$2:$I$201) -> 11902.28 | I4: =COUNTIF(Dataset!$C$2:$C$201,A4) -> 39
A5: South | B5: =SUMIFS(Dataset!$E$2:$E$201,Dataset!$C$2:$C$201,$A5,Dataset!$D$2:$D$201,B$1) -> 9588.04 | C5: =SUMIFS(Dataset!$E$2:$E$201,Dataset!$C$2:$C$201,$A5,Dataset!$D$2:$D$201,C$1) -> 8393.63 | D5: =SUMIFS(Dataset!$E$2:$E$201,Dataset!$C$2:$C$201,$A5,Dataset!$D$2:$D$201,D$1) -> 11989.07 | E5: =SUMIFS(Dataset!$E$2:$E$201,Dataset!$C$2:$C$201,$A5,Dataset!$D$2:$D$201,E$1) -> 7982.73 | F5: =SUMIFS(Dataset!$E$2:$E$201,Dataset!$C$2:$C$201,$A5,Dataset!$D$2:$D$201,F$1) -> 2295.32 | G5: =SUM(B5:F5) -> 40248.79 | H5: =SUMIF(Dataset!$C$2:$C$201,A5,Dataset!$I$2:$I$201) -> 13691.91 | I5: =COUNTIF(Dataset!$C$2:$C$201,A5) -> 42
A6: West | B6: =SUMIFS(Dataset!$E$2:$E$201,Dataset!$C$2:$C$201,$A6,Dataset!$D$2:$D$201,B$1) -> 6691.17 | C6: =SUMIFS(Dataset!$E$2:$E$201,Dataset!$C$2:$C$201,$A6,Dataset!$D$2:$D$201,C$1) -> 10509.43 | D6: =SUMIFS(Dataset!$E$2:$E$201,Dataset!$C$2:$C$201,$A6,Dataset!$D$2:$D$201,D$1) -> 11372.44 | E6: =SUMIFS(Dataset!$E$2:$E$201,Dataset!$C$2:$C$201,$A6,Dataset!$D$2:$D$201,E$1) -> 9182.78 | F6: =SUMIFS(Dataset!$E$2:$E$201,Dataset!$C$2:$C$201,$A6,Dataset!$D$2:$D$201,F$1) -> 6327.76 | G6: =SUM(B6:F6) -> 44083.58 | H6: =SUMIF(Dataset!$C$2:$C$201,A6,Dataset!$I$2:$I$201) -> 14985.83 | I6: =COUNTIF(Dataset!$C$2:$C$201,A6) -> 43
A7: GRAND TOTAL | B7: =SUM(B2:B6) -> 47002.46 | C7: =SUM(C2:C6) -> 41927.59 | D7: =SUM(D2:D6) -> 41044 | E7: =SUM(E2:E6) -> 36612.89 | F7: =SUM(F2:F6) -> 28630.82 | G7: =SUM(G2:G6) -> 195217.76 | H7: =SUM(H2:H6) -> 68287.01 | I7: =SUM(I2:I6) -> 200

Sheet Executive Dashboard
A1: PR. 2 | SALES ANALYTICS DASHBOARD | B1: VALUE | C1: INSIGHT / DEFINITION
A2: Total Sales | B2: =SUM(Dataset!E2:E201) -> 195217.76 | C2: All transactions
A3: Total Profit | B3: =SUM(Dataset!I2:I201) -> 68287.01 | C3: Original profit
A4: Profit Margin | B4: =IFERROR(B3/B2,0) -> 0.34979917 | C4: Profit / Sales
A5: Total Transactions | B5: =COUNTA(Dataset!A2:A201) -> 200 | C5: Original records
A6: Unique Customers | B6: =COUNTA('Customer Ranking'!A2:A31) -> 30 | C6: Distinct customer IDs
A7: Average Discount | B7: =AVERAGE(Dataset!G2:G201) -> 0.09725 | C7: Average of transaction discounts
A8: Top Customer | B8: ='Customer Ranking'!A2 -> CUST015 | C8: Highest cumulative purchase
A9: Best Sales Region | B9: =INDEX('Region Product Analysis'!A2:A6,MATCH(MAX('Region Product Analysis'!G2:G6),'Region Product Analysis'!G2:G6,0)) -> West | C9: Region with highest sales
A10: Best Product Category | B10: =INDEX('Region Product Analysis'!B1:F1,1,MATCH(MAX('Region Product Analysis'!B7:F7),'Region Product Analysis'!B7:F7,0)) -> Books | C10: Category with highest sales
A13: SALES BY REGION | B13: SALES | C13: PROFIT
A14: Central | B14: =SUMIF(Dataset!C2:C201,A14,Dataset!E2:E201) -> 43468.33 | C14: =SUMIF(Dataset!C2:C201,A14,Dataset!I2:I201) -> 16068.4
A15: East | B15: =SUMIF(Dataset!C2:C201,A15,Dataset!E2:E201) -> 32441.64 | C15: =SUMIF(Dataset!C2:C201,A15,Dataset!I2:I201) -> 11638.59
A16: North | B16: =SUMIF(Dataset!C2:C201,A16,Dataset!E2:E201) -> 34975.42 | C16: =SUMIF(Dataset!C2:C201,A16,Dataset!I2:I201) -> 11902.28
A17: South | B17: =SUMIF(Dataset!C2:C201,A17,Dataset!E2:E201) -> 40248.79 | C17: =SUMIF(Dataset!C2:C201,A17,Dataset!I2:I201) -> 13691.91
A18: West | B18: =SUMIF(Dataset!C2:C201,A18,Dataset!E2:E201) -> 44083.58 | C18: =SUMIF(Dataset!C2:C201,A18,Dataset!I2:I201) -> 14985.83
A21: SALES BY PRODUCT | B21: SALES | C21: PROFIT
A22: Books | B22: =SUMIF(Dataset!D2:D201,A22,Dataset!E2:E201) -> 47002.46 | C22: =SUMIF(Dataset!D2:D201,A22,Dataset!I2:I201) -> 16901.63
A23: Clothing | B23: =SUMIF(Dataset!D2:D201,A23,Dataset!E2:E201) -> 41927.59 | C23: =SUMIF(Dataset!D2:D201,A23,Dataset!I2:I201) -> 18784.49
A24: Electronics | B24: =SUMIF(Dataset!D2:D201,A24,Dataset!E2:E201) -> 41044 | C24: =SUMIF(Dataset!D2:D201,A24,Dataset!I2:I201) -> 9182.15
A25: Furniture | B25: =SUMIF(Dataset!D2:D201,A25,Dataset!E2:E201) -> 36612.89 | C25: =SUMIF(Dataset!D2:D201,A25,Dataset!I2:I201) -> 11579.14
A26: Office Supplies | B26: =SUMIF(Dataset!D2:D201,A26,Dataset!E2:E201) -> 28630.82 | C26: =SUMIF(Dataset!D2:D201,A26,Dataset!I2:I201) -> 11839.6
A30: MONTH | B30: SALES | C30: PROFIT
A31: 2024-04 | B31: =SUMIF(Dataset!L2:L201,A31,Dataset!E2:E201) -> 19029.96 | C31: =SUMIF(Dataset!L2:L201,A31,Dataset!I2:I201) -> 6244.01
A32: 2024-05 | B32: =SUMIF(Dataset!L2:L201,A32,Dataset!E2:E201) -> 18507.34 | C32: =SUMIF(Dataset!L2:L201,A32,Dataset!I2:I201) -> 6121.35
A33: 2024-06 | B33: =SUMIF(Dataset!L2:L201,A33,Dataset!E2:E201) -> 20187.51 | C33: =SUMIF(Dataset!L2:L201,A33,Dataset!I2:I201) -> 6918
A34: 2024-07 | B34: =SUMIF(Dataset!L2:L201,A34,Dataset!E2:E201) -> 11609.04 | C34: =SUMIF(Dataset!L2:L201,A34,Dataset!I2:I201) -> 3743.85
A35: 2024-08 | B35: =SUMIF(Dataset!L2:L201,A35,Dataset!E2:E201) -> 10091.7 | C35: =SUMIF(Dataset!L2:L201,A35,Dataset!I2:I201) -> 3302.84
A36: 2024-09 | B36: =SUMIF(Dataset!L2:L201,A36,Dataset!E2:E201) -> 20533.5 | C36: =SUMIF(Dataset!L2:L201,A36,Dataset!I2:I201) -> 7457.52
A37: 2024-10 | B37: =SUMIF(Dataset!L2:L201,A37,Dataset!E2:E201) -> 14215.24 | C37: =SUMIF(Dataset!L2:L201,A37,Dataset!I2:I201) -> 4861.7
A38: 2024-11 | B38: =SUMIF(Dataset!L2:L201,A38,Dataset!E2:E201) -> 20135.03 | C38: =SUMIF(Dataset!L2:L201,A38,Dataset!I2:I201) -> 6814.88
A39: 2024-12 | B39: =SUMIF(Dataset!L2:L201,A39,Dataset!E2:E201) -> 11120.04 | C39: =SUMIF(Dataset!L2:L201,A39,Dataset!I2:I201) -> 3549.99
A40: 2025-01 | B40: =SUMIF(Dataset!L2:L201,A40,Dataset!E2:E201) -> 14914.65 | C40: =SUMIF(Dataset!L2:L201,A40,Dataset!I2:I201) -> 5763.4
A41: 2025-02 | B41: =SUMIF(Dataset!L2:L201,A41,Dataset!E2:E201) -> 14006.36 | C41: =SUMIF(Dataset!L2:L201,A41,Dataset!I2:I201) -> 5039.23
A42: 2025-03 | B42: =SUMIF(Dataset!L2:L201,A42,Dataset!E2:E201) -> 17655.22 | C42: =SUMIF(Dataset!L2:L201,A42,Dataset!I2:I201) -> 7071.39
A43: 2025-04 | B43: =SUMIF(Dataset!L2:L201,A43,Dataset!E2:E201) -> 3212.17 | C43: =SUMIF(Dataset!L2:L201,A43,Dataset!I2:I201) -> 1398.85

Sheet Sales Histogram
A1: Sales Band Lower | B1: Sales Band Upper | C1: Transaction Count
A2: 0 | B2: 250 | C2: =COUNTIFS(Dataset!$E$2:$E$201,">="&A2,Dataset!$E$2:$E$201,"<"&B2) -> 0
A3: 250 | B3: 500 | C3: =COUNTIFS(Dataset!$E$2:$E$201,">="&A3,Dataset!$E$2:$E$201,"<"&B3) -> 11
A4: 500 | B4: 750 | C4: =COUNTIFS(Dataset!$E$2:$E$201,">="&A4,Dataset!$E$2:$E$201,"<"&B4) -> 37
A5: 750 | B5: 1000 | C5: =COUNTIFS(Dataset!$E$2:$E$201,">="&A5,Dataset!$E$2:$E$201,"<"&B5) -> 58
A6: 1000 | B6: 1250 | C6: =COUNTIFS(Dataset!$E$2:$E$201,">="&A6,Dataset!$E$2:$E$201,"<"&B6) -> 60
A7: 1250 | B7: 1500 | C7: =COUNTIFS(Dataset!$E$2:$E$201,">="&A7,Dataset!$E$2:$E$201,"<"&B7) -> 25
A8: 1500 | B8: 1750 | C8: =COUNTIFS(Dataset!$E$2:$E$201,">="&A8,Dataset!$E$2:$E$201,"<"&B8) -> 8
A9: 1750 | B9: 2000 | C9: =COUNTIFS(Dataset!$E$2:$E$201,">="&A9,Dataset!$E$2:$E$201,"<"&B9) -> 1
A10: 2000 | B10: 2250 | C10: =COUNTIFS(Dataset!$E$2:$E$201,">="&A10,Dataset!$E$2:$E$201,"<"&B10) -> 0
A11: 2250 | B11: 2500 | C11: =COUNTIFS(Dataset!$E$2:$E$201,">="&A11,Dataset!$E$2:$E$201,"<"&B11) -> 0
